mle_toolkit/__init__.py
mle_toolkit/callback_util.py
mle_toolkit/device_util.py
mle_toolkit/file_util.py
mle_toolkit/logger_util.py
mle_toolkit/module_util.py
mle_toolkit/optuna_util.py
mle_toolkit/pandas_util.py
mle_toolkit/parquet_util.py
mle_toolkit/path_util.py
mle_toolkit-0.7.dist-info/LICENSE
mle_toolkit-0.7.dist-info/METADATA
mle_toolkit-0.7.dist-info/WHEEL
mle_toolkit-0.7.dist-info/top_level.txt
mle_toolkit-0.7.dist-info/RECORD
