Metadata-Version: 2.1
Name: mle-toolkit
Version: 0.7
Summary: Machine Learning Experiment Toolkit.
Home-page: https://github.com/darkhan-ai/mle-toolkit
License: MIT
License-File: LICENSE
Requires-Dist: optuna
Requires-Dist: pandas
